txq_messages/__init__.py
txq_messages/base_message.py
txq_messages/response_message.py
txq_messages/secure_message.py
txq_messages-0.1.0.dist-info/LICENSE
txq_messages-0.1.0.dist-info/METADATA
txq_messages-0.1.0.dist-info/WHEEL
txq_messages-0.1.0.dist-info/top_level.txt
txq_messages-0.1.0.dist-info/zip-safe
txq_messages-0.1.0.dist-info/RECORD
