Metadata-Version: 2.1
Name: txq-messages
Version: 0.1.0
Summary: Message prototypes for TXQ Framework
Home-page: https://github.com/agratoth/txq-messages
Maintainer: Anton Berdnikov
Maintainer-email: agratoth@yandex.ru
License: UNKNOWN
Platform: UNKNOWN
Classifier: License :: OSI Approved :: MIT License
Classifier: Operating System :: OS Independent
Classifier: Programming Language :: Python
Classifier: Programming Language :: Python :: 3.8
Classifier: Programming Language :: Python :: 3.9
Requires-Python: >=3.8
